voi_lib/__init__.py
voi_lib/chatbot.py
voi_lib/config.py
voi_lib/utils.py
voichatlib-0.1.6.dist-info/LICENSE
voichatlib-0.1.6.dist-info/METADATA
voichatlib-0.1.6.dist-info/WHEEL
voichatlib-0.1.6.dist-info/top_level.txt
voichatlib-0.1.6.dist-info/RECORD
